omapper/__init__.py
omapper/exceptions.py
omapper/mapper.py
omapper/omapper_types.py
omapper-0.0.1a1.dist-info/LICENSE
omapper-0.0.1a1.dist-info/METADATA
omapper-0.0.1a1.dist-info/WHEEL
omapper-0.0.1a1.dist-info/top_level.txt
omapper-0.0.1a1.dist-info/RECORD
