Metadata-Version: 2.1
Name: omapper
Version: 0.0.1a1
Summary: Object Mapper
Home-page: http://github.com/eugenma/omapper
Author: Eugen Massini
Author-email: eugen@massini.de
License: MIT
Platform: UNKNOWN
Classifier: Development Status :: 1 - Planning
Classifier: License :: OSI Approved :: MIT License
Classifier: Programming Language :: Python :: 3.8
Classifier: Topic :: Software Development :: Libraries :: Python Modules
